{
  "processedProjects": 2,
  "totalProjects": 2,
  "projects": {
    "Samuel_Kim/uk_ulb_3jn_book": {
      "fullName": "Samuel_Kim/uk_ulb_3jn_book",
      "wA": {
        "langId": "uk",
        "projectId": "ulb",
        "bookId": "3jn",
        "percentCompleted": 0,
        "completedVerses": 0,
        "totalVerses": 15,
        "unalignedOrig": 219,
        "unalignedTarget": 228
      },
      "checks": {
        "langId": "uk",
        "projectId": "ulb",
        "bookId": "3jn",
        "time_created": "2021-04-05T06:55:48.531Z",
        "tc_edit_version": "3.0.1",
        "tc_version": 7,
        "translationNotes": {
          "percentCompleted": 0,
          "completedChecks": 0,
          "totalChecks": 20
        },
        "translationWords": {
          "toolData": {},
          "percentCompleted": 0,
          "completedChecks": 0,
          "totalChecks": 63,
          "stats": {
            "dupes": {},
            "migrations": {
              "data": {
                "glVersion": "v0"
              }
            },
            "toolWarnings": ""
          }
        },
        "wordAlignment": {
          "toolData": {
            "SelectedGL": "en"
          }
        }
      },
      "checkMigration": true,
      "modified": "2021-04-05T06:57:13Z"
    }
  }
}
